SONYC_CAPSTONE_VIS
