Metadata-Version: 1.0
Name: SONYC-CAPSTONE-VIS
Version: 0.3.2
Summary: SONYC Capstone Visualization Pacakge
Home-page: https://github.com/Distancs/SONYC_CAPSTONE_VIS
Author: Biao
Author-email: biaoh66@gmail.com
License: MIT
Keywords: SONYC,visualization
Platform: any
